ipyx/__init__.py
ipyx/_frontend.py
ipyx/_version.py
ipyx/f.py
ipyx/x.py
ipyx/labextension/package.json
ipyx/labextension/static/480.032f16358409a9c74f21.js
ipyx/labextension/static/480.1f11d803503e94180af1.js
ipyx/labextension/static/480.30851922624181b17d98.js
ipyx/labextension/static/480.71500bb42fd565d48bb3.js
ipyx/labextension/static/568.884b0c444d46f090edcf.js
ipyx/labextension/static/568.8ab89be498a92ac5bd4d.js
ipyx/labextension/static/568.978d79758de53c3e3272.js
ipyx/labextension/static/568.bce0f6dca9932299f7bb.js
ipyx/labextension/static/remoteEntry.0f92785e4cb94d8dc8e4.js
ipyx/labextension/static/remoteEntry.3fcba8834e670b0a6a55.js
ipyx/labextension/static/remoteEntry.6813b7b54e4160a6a3b0.js
ipyx/labextension/static/remoteEntry.95f4cae04f9a82de5aeb.js
ipyx/labextension/static/style.js
ipyx/labextension/static/third-party-licenses.json
ipyx/nbextension/extension.js
ipyx/nbextension/index.js
ipyx/nbextension/index.js.map
ipyx/tests/__init__.py
ipyx/tests/conftest.py
ipyx/tests/test_example.py
ipyx/tests/test_nbextension_path.py
ipyx-0.1.8.data/data/etc/jupyter/nbconfig/notebook.d/ipyx.json
ipyx-0.1.8.data/data/share/jupyter/labextensions/ipyx/install.json
ipyx-0.1.8.data/data/share/jupyter/labextensions/ipyx/package.json
ipyx-0.1.8.data/data/share/jupyter/labextensions/ipyx/static/480.032f16358409a9c74f21.js
ipyx-0.1.8.data/data/share/jupyter/labextensions/ipyx/static/568.8ab89be498a92ac5bd4d.js
ipyx-0.1.8.data/data/share/jupyter/labextensions/ipyx/static/remoteEntry.0f92785e4cb94d8dc8e4.js
ipyx-0.1.8.data/data/share/jupyter/labextensions/ipyx/static/style.js
ipyx-0.1.8.data/data/share/jupyter/labextensions/ipyx/static/third-party-licenses.json
ipyx-0.1.8.data/data/share/jupyter/nbextensions/ipyx/extension.js
ipyx-0.1.8.data/data/share/jupyter/nbextensions/ipyx/index.js
ipyx-0.1.8.data/data/share/jupyter/nbextensions/ipyx/index.js.map
ipyx-0.1.8.dist-info/LICENSE.txt
ipyx-0.1.8.dist-info/METADATA
ipyx-0.1.8.dist-info/WHEEL
ipyx-0.1.8.dist-info/top_level.txt
ipyx-0.1.8.dist-info/RECORD
