Metadata-Version: 2.1
Name: ipyx
Version: 0.1.8
Summary: A Jupyter widget library for reactive variables
Home-page: https://github.com/davidbrochart/ipyx
Author: David Brochart
Author-email: david.brochart@gmail.com
License: BSD
Keywords: Jupyter,Widgets,IPython
Platform: Linux
Platform: Mac OS X
Platform: Windows
Classifier: Intended Audience :: Developers
Classifier: Intended Audience :: Science/Research
Classifier: License :: OSI Approved :: BSD License
Classifier: Programming Language :: Python
Classifier: Programming Language :: Python :: 3
Classifier: Programming Language :: Python :: 3.4
Classifier: Programming Language :: Python :: 3.5
Classifier: Programming Language :: Python :: 3.6
Classifier: Programming Language :: Python :: 3.7
Classifier: Framework :: Jupyter
Requires-Python: >=3.6
License-File: LICENSE.txt
Requires-Dist: ipywidgets (>=7.0.0)
Requires-Dist: ipycytoscape
Provides-Extra: docs
Requires-Dist: jupyter-sphinx ; extra == 'docs'
Requires-Dist: nbsphinx ; extra == 'docs'
Requires-Dist: nbsphinx-link ; extra == 'docs'
Requires-Dist: pytest-check-links ; extra == 'docs'
Requires-Dist: pypandoc ; extra == 'docs'
Requires-Dist: recommonmark ; extra == 'docs'
Requires-Dist: sphinx (>=1.5) ; extra == 'docs'
Requires-Dist: sphinx-rtd-theme ; extra == 'docs'
Provides-Extra: examples
Provides-Extra: test
Requires-Dist: pytest (>=4.6) ; extra == 'test'
Requires-Dist: pytest-cov ; extra == 'test'
Requires-Dist: nbval ; extra == 'test'
